mediaserver/__init__.py
mediaserver/video.py
videopy-0.0.1.2.dist-info/DESCRIPTION.rst
videopy-0.0.1.2.dist-info/METADATA
videopy-0.0.1.2.dist-info/RECORD
videopy-0.0.1.2.dist-info/WHEEL
videopy-0.0.1.2.dist-info/entry_points.txt
videopy-0.0.1.2.dist-info/metadata.json
videopy-0.0.1.2.dist-info/top_level.txt
