Metadata-Version: 2.0
Name: videopy
Version: 0.0.1.2
Summary: HTTP Media Server for VLC
Home-page: https://github.com/animeshkundu/media-server
Author: Animesh Kundu
Author-email: anik.edu@gmail.com
License: LICENSE.txt
Platform: UNKNOWN
Requires-Dist: netifaces (==0.10.5)
